packed_anagram_hash/__init__.py
packed_anagram_hash/hasher.py
packed_anagram_hash-1.0.1.dist-info/METADATA
packed_anagram_hash-1.0.1.dist-info/WHEEL
packed_anagram_hash-1.0.1.dist-info/licenses/LICENSE
packed_anagram_hash-1.0.1.dist-info/RECORD
