Metadata-Version: 2.4
Name: packed-anagram-hash
Version: 1.0.1
Summary: Constant-time anagram hashing using packed bit-width representation
Project-URL: Documentation, https://github.com/worldbridgerstudios/packed-anagram-hash#readme
Project-URL: Paper, https://doi.org/10.5281/zenodo.18167975
Project-URL: Repository, https://github.com/worldbridgerstudios/packed-anagram-hash
Author-email: Nicholas David Brown <worldbridgerstudios@gmail.com>
License-Expression: CC0-1.0
License-File: LICENSE
Keywords: algorithm,anagram,bit-manipulation,computational-linguistics,hashing,nlp,string-matching
Classifier: Development Status :: 5 - Production/Stable
Classifier: Intended Audience :: Developers
Classifier: Intended Audience :: Science/Research
Classifier: License :: CC0 1.0 Universal (CC0 1.0) Public Domain Dedication
Classifier: Operating System :: OS Independent
Classifier: Programming Language :: Python :: 3
Classifier: Programming Language :: Python :: 3.8
Classifier: Programming Language :: Python :: 3.9
Classifier: Programming Language :: Python :: 3.10
Classifier: Programming Language :: Python :: 3.11
Classifier: Programming Language :: Python :: 3.12
Classifier: Topic :: Scientific/Engineering
Classifier: Topic :: Text Processing :: Linguistic
Requires-Python: >=3.8
